chatique/__init__.py
chatique/chatique.py
cmes/__init__.py
cmes/chatic.py
chatique-1.0.2.dist-info/METADATA
chatique-1.0.2.dist-info/WHEEL
chatique-1.0.2.dist-info/top_level.txt
chatique-1.0.2.dist-info/RECORD
